pydaconf/__init__.py
pydaconf/cli.py
pydaconf/main.py
pydaconf/plugins/__init__.py
pydaconf/plugins/base.py
pydaconf/plugins/env.py
pydaconf/plugins/file_content.py
pydaconf/plugins/sealed.py
pydaconf/utils/__init__.py
pydaconf/utils/dict.py
pydaconf/utils/exceptions.py
pydaconf/utils/file.py
pydaconf/utils/interpolation.py
pydaconf/utils/plugins.py
pydaconf-0.1.0.dist-info/entry_points.txt
pydaconf-0.1.0.dist-info/LICENSE
pydaconf-0.1.0.dist-info/WHEEL
pydaconf-0.1.0.dist-info/METADATA
pydaconf-0.1.0.dist-info/RECORD
