Metadata-Version: 2.3
Name: pydaconf
Version: 0.1.0
Summary: Configuration file provider that uses pydantic and type hints.
Author-email: Borislav Varadinov <borislav.varadinov@outlook.com>
Requires-Python: >=3.10
Classifier: Development Status :: 4 - Beta
Classifier: Intended Audience :: Developers
Classifier: License :: OSI Approved :: MIT License
Classifier: Programming Language :: Python :: 3
Classifier: Programming Language :: Python :: 3 :: Only
Classifier: Programming Language :: Python :: 3.8
Classifier: Programming Language :: Python :: 3.9
Classifier: Programming Language :: Python :: 3.10
Classifier: Programming Language :: Python :: 3.11
Classifier: Programming Language :: Python :: 3.12
Classifier: Programming Language :: Python :: 3.13
Classifier: Topic :: Internet
Classifier: Topic :: Software Development :: Libraries :: Python Modules
Classifier: Topic :: Software Development :: Libraries
Classifier: Topic :: Software Development
Classifier: Typing :: Typed
Requires-Dist: pydantic>=2.0.1
Requires-Dist: python-dotenv>=1.0.1
Requires-Dist: tomli>=2.0.1 ; extra == "all"
Requires-Dist: pyyaml>=6.0.1 ; extra == "all"
Requires-Dist: requests>=2.32.3 ; extra == "all"
Requires-Dist: cryptography>=44.0.0 ; extra == "all"
Requires-Dist: typer==0.15.1 ; extra == "all"
Requires-Dist: typer==0.15.1 ; extra == "cli"
Requires-Dist: cryptography>=44.0.0 ; extra == "cryptography"
Requires-Dist: requests>=2.32.3 ; extra == "requests"
Requires-Dist: tomli>=2.0.1 ; extra == "toml"
Requires-Dist: pyyaml>=6.0.1 ; extra == "yaml"
Project-URL: Documentation, https://varadinov.github.io/pydaconf/
Project-URL: Homepage, https://github.com/varadinov/pydaconf
Project-URL: Issues, https://github.com/varadinov/pydaconf/issues
Project-URL: Repository, https://github.com/varadinov/pydaconf
Provides-Extra: all
Provides-Extra: cli
Provides-Extra: cryptography
Provides-Extra: requests
Provides-Extra: toml
Provides-Extra: yaml
